hclib.py
hclib-1.0.4.dist-info/METADATA
hclib-1.0.4.dist-info/RECORD
hclib-1.0.4.dist-info/WHEEL
hclib-1.0.4.dist-info/top_level.txt
