Metadata-Version: 2.1
Name: hclib
Version: 1.0.4
Summary: A library to connect to https://hack.chat/
Home-page: https://github.com/neelkamath/hclib
Author: Neel Kamath
Author-email: neelkamath@icloud.com
License: MIT
Keywords: hack.chat library
Platform: UNKNOWN
Classifier: Programming Language :: Python :: 3
Classifier: License :: OSI Approved :: MIT License
Classifier: Operating System :: OS Independent
Requires-Dist: websocket-client (<1,>=0.44)
